[
  {
    "path": "/mnt/music_ssd/KKDJ/sorted/B/Big Nuz/Big Nuz Osisi Bendawo - 10A - 125.mp3",
    "reason": "guardrail_violation",
    "details": ""
  },
  {
    "path": "/mnt/music_ssd/KKDJ/sorted/B/Big Nuz/Big Nuz Phaqa - 8A - 126.mp3",
    "reason": "guardrail_violation",
    "details": ""
  },
  {
    "path": "/mnt/music_ssd/KKDJ/sorted/B/Big Nuz/Big Nuz Tsege Tsege - 2A - 126.mp3",
    "reason": "guardrail_violation",
    "details": ""
  },
  {
    "path": "/mnt/music_ssd/KKDJ/sorted/B/Big Nuz X Babes Wodumo & DJ Tira/Big Nuz X Babes Wodumo & DJ Tira Amatsegetsege (Argento Dust Remix) - 7A - 126.mp3",
    "reason": "guardrail_violation",
    "details": ""
  },
  {
    "path": "/mnt/music_ssd/KKDJ/sorted/B/Black Cofee Feat. Bucie/Black Cofee Feat. Bucie Superman (Afro Dj Pupo's Ancestry Children Tune) - 4A - 123.mp3",
    "reason": "guardrail_violation",
    "details": ""
  },
  {
    "path": "/mnt/music_ssd/KKDJ/sorted/B/Black Coffee/Black Coffee - Angelina - 7A - 124.mp3",
    "reason": "guardrail_violation",
    "details": ""
  },
  {
    "path": "/mnt/music_ssd/KKDJ/sorted/B/Black Coffee/Black Coffee - Any Other Way - 12A - 124.mp3",
    "reason": "low_confidence",
    "details": ""
  },
  {
    "path": "/mnt/music_ssd/KKDJ/sorted/B/Black Coffee/Black Coffee - Crazy - 5A - 124.mp3",
    "reason": "guardrail_violation",
    "details": ""
  },
  {
    "path": "/mnt/music_ssd/KKDJ/sorted/B/Black Coffee/Black Coffee - Extra Time on You - 5A - 124.mp3",
    "reason": "guardrail_violation",
    "details": ""
  },
  {
    "path": "/mnt/music_ssd/KKDJ/sorted/B/Black Coffee/Black Coffee - Gardens of Eden - 2A - 124.mp3",
    "reason": "guardrail_violation",
    "details": ""
  },
  {
    "path": "/mnt/music_ssd/KKDJ/sorted/B/Black Coffee/Black Coffee - I Have Faith - 6A - 124.mp3",
    "reason": "guardrail_violation",
    "details": ""
  },
  {
    "path": "/mnt/music_ssd/KKDJ/sorted/B/Black Coffee/Black Coffee - Inseparable - 9A - 124.mp3",
    "reason": "guardrail_violation",
    "details": ""
  },
  {
    "path": "/mnt/music_ssd/KKDJ/sorted/B/Black Coffee/Black Coffee - Juju - 2A - 124.mp3",
    "reason": "guardrail_violation",
    "details": ""
  },
  {
    "path": "/mnt/music_ssd/KKDJ/sorted/B/Black Coffee/Black Coffee - Kwanele (Black Coffee Remix) - 1A - 123.mp3",
    "reason": "guardrail_violation",
    "details": ""
  },
  {
    "path": "/mnt/music_ssd/KKDJ/sorted/B/Black Coffee/Black Coffee - Love on Fire - 10A - 124.mp3",
    "reason": "guardrail_violation",
    "details": ""
  },
  {
    "path": "/mnt/music_ssd/KKDJ/sorted/B/Black Coffee/Black Coffee - Mama - 5A - 124.mp3",
    "reason": "guardrail_violation",
    "details": ""
  },
  {
    "path": "/mnt/music_ssd/KKDJ/sorted/B/Black Coffee/Black Coffee - Never Saw You Coming - 3A - 124.mp3",
    "reason": "guardrail_violation",
    "details": ""
  },
  {
    "path": "/mnt/music_ssd/KKDJ/sorted/B/Black Coffee/Black Coffee - Someday - 2A - 124.mp3",
    "reason": "guardrail_violation",
    "details": ""
  },
  {
    "path": "/mnt/music_ssd/KKDJ/sorted/B/Black Coffee/Black Coffee Feat. Bucie Finish Line (Original) - 8A - 124.mp3",
    "reason": "guardrail_violation",
    "details": ""
  },
  {
    "path": "/mnt/music_ssd/KKDJ/sorted/B/Black Coffee/Black Coffee Feat. Soulstar Rock My World (Enawadan Remix) - 3A - 123.mp3",
    "reason": "guardrail_violation",
    "details": ""
  },
  {
    "path": "/mnt/music_ssd/KKDJ/sorted/B/Black Coffee/Black Coffee Feat. Zakes Bantwini Juju (Bekzin Tetris Remix) - 2A - 125.mp3",
    "reason": "guardrail_violation",
    "details": ""
  },
  {
    "path": "/mnt/music_ssd/KKDJ/sorted/B/Black Coffee/Black Coffee Ft. Soulstar Rock My World (Rancido's Travelling Soul Remix) - 3A - 123.mp3",
    "reason": "guardrail_violation",
    "details": ""
  },
  {
    "path": "/mnt/music_ssd/KKDJ/sorted/B/Black Coffee/Black Coffee Trip To Lyon - 11A - 125.mp3",
    "reason": "guardrail_violation",
    "details": ""
  },
  {
    "path": "/mnt/music_ssd/KKDJ/sorted/B/Black Coffee/Black Coffee ft. Cara I Will Find You (Original) - 8A - 125.mp3",
    "reason": "guardrail_violation",
    "details": ""
  },
  {
    "path": "/mnt/music_ssd/KKDJ/sorted/B/Black Coffee/Black Coffee, Busi Mhlongo Izizwe - 4A - 123.mp3",
    "reason": "guardrail_violation",
    "details": ""
  },
  {
    "path": "/mnt/music_ssd/KKDJ/sorted/B/Black Coffee/Black Coffee, Karyendasoul Any Other Way (feat. Zhao) - 12A - 124.mp3",
    "reason": "guardrail_violation",
    "details": ""
  },
  {
    "path": "/mnt/music_ssd/KKDJ/sorted/B/Black Coffee/Black Coffee, Nomsa Mazwai & Black Motion Traveller - 9A - 125.mp3",
    "reason": "guardrail_violation",
    "details": ""
  },
  {
    "path": "/mnt/music_ssd/KKDJ/sorted/B/Black Coffee & Bucie/Black Coffee & Bucie Superman (Main Mix) (1) - 4A - 123.mp3",
    "reason": "guardrail_violation",
    "details": ""
  },
  {
    "path": "/mnt/music_ssd/KKDJ/sorted/B/Black Coffee & Bucie/Black Coffee & Bucie Superman (Main Mix) - 4A - 123.mp3",
    "reason": "guardrail_violation",
    "details": ""
  },
  {
    "path": "/mnt/music_ssd/KKDJ/sorted/B/Black Coffee & Karyendasoul/Black Coffee & Karyendasoul Thando (feat. Mbuso Khoza) - 6A - 123.mp3",
    "reason": "guardrail_violation",
    "details": ""
  },
  {
    "path": "/mnt/music_ssd/KKDJ/sorted/B/Black Coffee Msaki/Black Coffee Msaki - Wish You Were (Bedouin Remix) - 8A - 123.mp3",
    "reason": "guardrail_violation",
    "details": ""
  },
  {
    "path": "/mnt/music_ssd/KKDJ/sorted/B/Black Coffee Pharrel Williams Jozzy/Black Coffee Pharrel Williams Jozzy Missed Calls (1) - 3A - 108.mp3",
    "reason": "guardrail_violation",
    "details": ""
  },
  {
    "path": "/mnt/music_ssd/KKDJ/sorted/B/Black Coffee Pharrel Williams Jozzy/Black Coffee Pharrel Williams Jozzy Missed Calls - 3A - 108.mp3",
    "reason": "low_confidence",
    "details": ""
  },
  {
    "path": "/mnt/music_ssd/KKDJ/sorted/B/Black Coffee Thiwe/Black Coffee Thiwe - Crazy (Culoe De Song Winter Remix) - 6A - 124.mp3",
    "reason": "guardrail_violation",
    "details": ""
  },
  {
    "path": "/mnt/music_ssd/KKDJ/sorted/B/Black Coffee Thiwe/Black Coffee Thiwe - Crazy (Manoo & Francois Aymonier Remix) - 5A - 124.mp3",
    "reason": "guardrail_violation",
    "details": ""
  },
  {
    "path": "/mnt/music_ssd/KKDJ/sorted/B/Black Coffee Thiwe/Black Coffee Thiwe - Crazy (Quentin Harris remix) - 5A - 124.mp3",
    "reason": "guardrail_violation",
    "details": ""
  },
  {
    "path": "/mnt/music_ssd/KKDJ/sorted/B/Black Coffee Tsepo/Black Coffee Tsepo - Never Saw You Coming (DJ Spinna Galactic Vocal Mix) - 3A - 123.mp3",
    "reason": "guardrail_violation",
    "details": ""
  },
  {
    "path": "/mnt/music_ssd/KKDJ/sorted/B/Black Coffee Tsepo/Black Coffee Tsepo - Never Saw You Coming (Franck Roger Vocal Mix) - 1A - 123.mp3",
    "reason": "guardrail_violation",
    "details": ""
  },
  {
    "path": "/mnt/music_ssd/KKDJ/sorted/B/Black Coffee Tsepo/Black Coffee Tsepo - Never Saw You Coming (Original Mix) - 3A - 123.mp3",
    "reason": "guardrail_violation",
    "details": ""
  },
  {
    "path": "/mnt/music_ssd/KKDJ/sorted/B/Black Motion/Black Motion - Africana - 6A - 125.mp3",
    "reason": "guardrail_violation",
    "details": ""
  },
  {
    "path": "/mnt/music_ssd/KKDJ/sorted/B/Black Motion/Black Motion - Anyway - 7A - 124.mp3",
    "reason": "guardrail_violation",
    "details": ""
  },
  {
    "path": "/mnt/music_ssd/KKDJ/sorted/B/Black Motion/Black Motion - Bambolwam - 2A - 123.mp3",
    "reason": "guardrail_violation",
    "details": ""
  },
  {
    "path": "/mnt/music_ssd/KKDJ/sorted/B/Black Motion/Black Motion - Drums of Africa - 9A - 125.mp3",
    "reason": "guardrail_violation",
    "details": ""
  },
  {
    "path": "/mnt/music_ssd/KKDJ/sorted/B/Black Motion/Black Motion - Electronic Maskandi - 2A - 125.mp3",
    "reason": "guardrail_violation",
    "details": ""
  },
  {
    "path": "/mnt/music_ssd/KKDJ/sorted/B/Black Motion/Black Motion - I Wanna Be - 4A - 120.mp3",
    "reason": "low_confidence",
    "details": ""
  },
  {
    "path": "/mnt/music_ssd/KKDJ/sorted/B/Black Motion/Black Motion - Imali - 11A - 123.mp3",
    "reason": "guardrail_violation",
    "details": ""
  },
  {
    "path": "/mnt/music_ssd/KKDJ/sorted/B/Black Motion/Black Motion - Linde Wena - 2A - 123.mp3",
    "reason": "guardrail_violation",
    "details": ""
  },
  {
    "path": "/mnt/music_ssd/KKDJ/sorted/B/Black Motion/Black Motion - Omo Dudu - 9A - 123.mp3",
    "reason": "guardrail_violation",
    "details": ""
  },
  {
    "path": "/mnt/music_ssd/KKDJ/sorted/B/Black Motion/Black Motion - Rainbow (DJ Spen & Michele Chiavarini remix) - 3A - 124.mp3",
    "reason": "guardrail_violation",
    "details": ""
  },
  {
    "path": "/mnt/music_ssd/KKDJ/sorted/B/Black Motion/Black Motion - Rainbow (feat. Xoli M) - 3A - 124.mp3",
    "reason": "guardrail_violation",
    "details": ""
  },
  {
    "path": "/mnt/music_ssd/KKDJ/sorted/B/Black Motion/Black Motion - Stametta (Black Motion Remix) - 11A - 119.mp3",
    "reason": "guardrail_violation",
    "details": ""
  },
  {
    "path": "/mnt/music_ssd/KKDJ/sorted/B/Black Motion/Black Motion - Teenage Love Affair - 8A - 124.mp3",
    "reason": "guardrail_violation",
    "details": ""
  },
  {
    "path": "/mnt/music_ssd/KKDJ/sorted/B/Black Motion/Black Motion - Ya Badimo - 10A - 123.mp3",
    "reason": "guardrail_violation",
    "details": ""
  },
  {
    "path": "/mnt/music_ssd/KKDJ/sorted/B/Black Motion/Black Motion - uGayo - 9A - 123.mp3",
    "reason": "guardrail_violation",
    "details": ""
  },
  {
    "path": "/mnt/music_ssd/KKDJ/sorted/B/Black Motion/Black Motion Dare Dance - 8A - 125.mp3",
    "reason": "guardrail_violation",
    "details": ""
  },
  {
    "path": "/mnt/music_ssd/KKDJ/sorted/B/Black Motion/Black Motion Dark Channels (1) - 7A - 125.mp3",
    "reason": "guardrail_violation",
    "details": ""
  },
  {
    "path": "/mnt/music_ssd/KKDJ/sorted/B/Black Motion/Black Motion Dranakuta - 9A - 124.mp3",
    "reason": "guardrail_violation",
    "details": ""
  },
  {
    "path": "/mnt/music_ssd/KKDJ/sorted/B/Black Motion/Black Motion Feat. Black Coffee & Xelimpilo Thamokuro - 10A - 125.mp3",
    "reason": "guardrail_violation",
    "details": ""
  },
  {
    "path": "/mnt/music_ssd/KKDJ/sorted/B/Black Motion/Black Motion Feat. Candy Manghoro - 3A - 127.mp3",
    "reason": "guardrail_violation",
    "details": ""
  },
  {
    "path": "/mnt/music_ssd/KKDJ/sorted/B/Black Motion/Black Motion Feat. Celimpilo Ndinokuda (I Love You) (Manoo's Aitf Remix) - 11A - 125.m4a",
    "reason": "guardrail_violation",
    "details": ""
  },
  {
    "path": "/mnt/music_ssd/KKDJ/sorted/B/Black Motion/Black Motion Feat. Monea Charity - 4A - 126.mp3",
    "reason": "guardrail_violation",
    "details": ""
  },
  {
    "path": "/mnt/music_ssd/KKDJ/sorted/B/Black Motion/Black Motion Fortune Teller (1) - 2A - 125.mp3",
    "reason": "guardrail_violation",
    "details": ""
  },
  {
    "path": "/mnt/music_ssd/KKDJ/sorted/B/Black Motion/Black Motion Fortune Teller(Spet Error & Znicho Remix) - 2A - 125.mp3",
    "reason": "guardrail_violation",
    "details": ""
  },
  {
    "path": "/mnt/music_ssd/KKDJ/sorted/B/Black Motion/Black Motion I Rise (feat. Msaki) - 3A - 125.mp3",
    "reason": "guardrail_violation",
    "details": ""
  },
  {
    "path": "/mnt/music_ssd/KKDJ/sorted/B/Black Motion/Black Motion Ikisha - 7A - 125.mp3",
    "reason": "guardrail_violation",
    "details": ""
  },
  {
    "path": "/mnt/music_ssd/KKDJ/sorted/B/Black Motion/Black Motion Imali (feat. Nokwazi) - 11A - 123.mp3",
    "reason": "guardrail_violation",
    "details": ""
  },
  {
    "path": "/mnt/music_ssd/KKDJ/sorted/B/Black Motion/Black Motion It's You (feat. Miss P) - 11A - 125.mp3",
    "reason": "guardrail_violation",
    "details": ""
  },
  {
    "path": "/mnt/music_ssd/KKDJ/sorted/B/Black Motion/Black Motion Mekgolokwane - 7A - 125.mp3",
    "reason": "guardrail_violation",
    "details": ""
  },
  {
    "path": "/mnt/music_ssd/KKDJ/sorted/B/Black Motion/Black Motion Mother Of Earth (Intro) KKDJ Afro INTRO (1) - 3A - 125.mp3",
    "reason": "guardrail_violation",
    "details": ""
  },
  {
    "path": "/mnt/music_ssd/KKDJ/sorted/B/Black Motion/Black Motion Mother Of Earth (Intro) KKDJ Afro INTRO - 3A - 125.mp3",
    "reason": "guardrail_violation",
    "details": ""
  },
  {
    "path": "/mnt/music_ssd/KKDJ/sorted/B/Black Motion/Black Motion Ngungunyane (feat. Mholi Vilakazi) - 11A - 124.mp3",
    "reason": "guardrail_violation",
    "details": ""
  },
  {
    "path": "/mnt/music_ssd/KKDJ/sorted/B/Black Motion/Black Motion Omo Dudu (feat. Wunmi) - 9A - 123.mp3",
    "reason": "guardrail_violation",
    "details": ""
  },
  {
    "path": "/mnt/music_ssd/KKDJ/sorted/B/Black Motion/Black Motion So Where To (feat TRESOR & The Mahotella Queens) - 1B - 123.mp3",
    "reason": "guardrail_violation",
    "details": ""
  },
  {
    "path": "/mnt/music_ssd/KKDJ/sorted/B/Black Motion/Black Motion Spirit Of Motion - 8A - 168.mp3",
    "reason": "guardrail_violation",
    "details": ""
  },
  {
    "path": "/mnt/music_ssd/KKDJ/sorted/B/Black Motion/Black Motion That Song (Tribute To Kwani Experience) - 3A - 125.mp3",
    "reason": "guardrail_violation",
    "details": ""
  },
  {
    "path": "/mnt/music_ssd/KKDJ/sorted/B/Black Motion/Black Motion The Journey - 11A - 123.mp3",
    "reason": "guardrail_violation",
    "details": ""
  },
  {
    "path": "/mnt/music_ssd/KKDJ/sorted/B/Black Motion/Black Motion Trap en Los (feat. Nokwazi) - 11A - 123.mp3",
    "reason": "guardrail_violation",
    "details": ""
  },
  {
    "path": "/mnt/music_ssd/KKDJ/sorted/B/Black Motion/Black Motion We As One difficult - 7A - 124.mp3",
    "reason": "guardrail_violation",
    "details": ""
  },
  {
    "path": "/mnt/music_ssd/KKDJ/sorted/B/Black Motion/Black Motion Ya Badimo (feat. Tlokwe Sehume) - 10A - 123.mp3",
    "reason": "guardrail_violation",
    "details": ""
  },
  {
    "path": "/mnt/music_ssd/KKDJ/sorted/B/Black Motion/Black Motion feat. Jah Rich Banane Mavoko (Real Clap) - 8A - 125.mp3",
    "reason": "guardrail_violation",
    "details": ""
  },
  {
    "path": "/mnt/music_ssd/KKDJ/sorted/B/Black Motion/Black Motion feat. Noumoucounda Cissoko Sheri - 6A - 124.mp3",
    "reason": "guardrail_violation",
    "details": ""
  },
  {
    "path": "/mnt/music_ssd/KKDJ/sorted/B/Black Motion/Black Motion feat. Xoli Set Me Free (Early Breeze Remix) - 11A - 124.mp3",
    "reason": "guardrail_violation",
    "details": ""
  },
  {
    "path": "/mnt/music_ssd/KKDJ/sorted/B/Black Motion/Black Motion feat. Xoli Set Me Free (MKTL Master Kev and Tony Loreto Remix) - 11A - 124.mp3",
    "reason": "guardrail_violation",
    "details": ""
  },
  {
    "path": "/mnt/music_ssd/KKDJ/sorted/B/Black Motion/Black Motion, Soulflow Mumi Wango (Main Mix) - 6A - 125.mp3",
    "reason": "guardrail_violation",
    "details": ""
  },
  {
    "path": "/mnt/music_ssd/KKDJ/sorted/B/Black Motion & Malehloka Hlalele/Black Motion & Malehloka Hlalele Don't Let Me Go ft. DJeff - 12A - 123.mp3",
    "reason": "guardrail_violation",
    "details": ""
  },
  {
    "path": "/mnt/music_ssd/KKDJ/sorted/B/Black Motion Xoli/Black Motion Xoli - Set Me Free (Bang the Drum Vocal Mix) - 11A - 126.mp3",
    "reason": "guardrail_violation",
    "details": ""
  },
  {
    "path": "/mnt/music_ssd/KKDJ/sorted/B/Black Motion Xoli/Black Motion Xoli - Set Me Free (Bang's Synth Dub) - 11A - 126.mp3",
    "reason": "guardrail_violation",
    "details": ""
  },
  {
    "path": "/mnt/music_ssd/KKDJ/sorted/B/Black Motion Xoli/Black Motion Xoli - Set Me Free (Early Breeze Remix) - 11A - 124.mp3",
    "reason": "guardrail_violation",
    "details": ""
  },
  {
    "path": "/mnt/music_ssd/KKDJ/sorted/B/Black Motion Xoli/Black Motion Xoli - Set Me Free (Ezel Remix) - 11A - 125.mp3",
    "reason": "guardrail_violation",
    "details": ""
  },
  {
    "path": "/mnt/music_ssd/KKDJ/sorted/B/Black Motion Xoli/Black Motion Xoli - Set Me Free (Mktl Master Kev and Tony Loreto Remix) - 11A - 124.mp3",
    "reason": "guardrail_violation",
    "details": ""
  },
  {
    "path": "/mnt/music_ssd/KKDJ/sorted/B/Black Motion Xoli/Black Motion Xoli - Set Me Free - 11A - 125.mp3",
    "reason": "guardrail_violation",
    "details": ""
  },
  {
    "path": "/mnt/music_ssd/KKDJ/sorted/B/Blackcoffee/BlackCoffee feat Zano Someday (1) - 2A - 124.mp3",
    "reason": "guardrail_violation",
    "details": ""
  },
  {
    "path": "/mnt/music_ssd/KKDJ/sorted/B/Blackcoffee/BlackCoffee feat Zano Someday - 2A - 124.mp3",
    "reason": "guardrail_violation",
    "details": ""
  },
  {
    "path": "/mnt/music_ssd/KKDJ/sorted/B/Bob Ezy/Emazulwini - 9A - 115.mp3",
    "reason": "guardrail_violation",
    "details": ""
  },
  {
    "path": "/mnt/music_ssd/KKDJ/sorted/B/Bob Marley/Bob Marley Is this love (Maphorisa n Clap Remix) - 8A - 125.mp3",
    "reason": "guardrail_violation",
    "details": ""
  },
  {
    "path": "/mnt/music_ssd/KKDJ/sorted/B/Bob Sinclar Feat. Shabba Ranks/Bob Sinclar Feat. Shabba Ranks Love You No More (Boddhi Satva Ancestral Dub) - 3A - 123.mp3",
    "reason": "guardrail_violation",
    "details": ""
  },
  {
    "path": "/mnt/music_ssd/KKDJ/sorted/B/Bobendanaka/Bobendanaka Afrika Beatz (Original) - 5A - 126.mp3",
    "reason": "guardrail_violation",
    "details": ""
  },
  {
    "path": "/mnt/music_ssd/KKDJ/sorted/B/Boddhi Satva/Boddhi Satva Kanga Mutu (feat. Spilulu & H-Baraka) (Ancestral Soul) - 2A - 124.mp3",
    "reason": "guardrail_violation",
    "details": ""
  },
  {
    "path": "/mnt/music_ssd/KKDJ/sorted/B/Boddhi Satva/Boddhi Satva feat. E-Man Sweet Brown Sugar (Eltonnick Remix) (1) - 11A - 123.mp3",
    "reason": "guardrail_violation",
    "details": ""
  },
  {
    "path": "/mnt/music_ssd/KKDJ/sorted/B/Boddhi Satva/Boddhi Satva feat. E-Man Sweet Brown Sugar (Eltonnick Remix) - 11A - 123.mp3",
    "reason": "guardrail_violation",
    "details": ""
  },
  {
    "path": "/mnt/music_ssd/KKDJ/sorted/B/Boddhi Satva/Boddhi Satva ft. Mangala Camara Nankoumandjan (Rancido's Deep Deep Journey Dub) - 1A - 123.mp3",
    "reason": "guardrail_violation",
    "details": ""
  },
  {
    "path": "/mnt/music_ssd/KKDJ/sorted/B/Boddhi Satva/Boddhi Satva, Maalem Hammam Zid Lmel (FNX Remix) (1) - 9A - 123.mp3",
    "reason": "guardrail_violation",
    "details": ""
  },
  {
    "path": "/mnt/music_ssd/KKDJ/sorted/B/Boddhi Satva/Boddhi Satva, Maalem Hammam Zid Lmel (FNX Remix) - 9A - 123.mp3",
    "reason": "low_confidence",
    "details": ""
  },
  {
    "path": "/mnt/music_ssd/KKDJ/sorted/B/Boddhi Satva/Boddhi Satva, Mehdi Nassouli Ghaita (Extended Mix) - 9A - 120.mp3",
    "reason": "guardrail_violation",
    "details": ""
  },
  {
    "path": "/mnt/music_ssd/KKDJ/sorted/B/Boddhi Satva/Boddhi Satva, Oumou Sangare Ngnari Konon - 9A - 121.mp3",
    "reason": "guardrail_violation",
    "details": ""
  },
  {
    "path": "/mnt/music_ssd/KKDJ/sorted/B/Boddhi Satva/Boddhi Satva, Spilulu, H-Baraka Kanga Mutu (LiloCox Remix 'Ancestral Soul Edit') - 1A - 125.mp3",
    "reason": "guardrail_violation",
    "details": ""
  },
  {
    "path": "/mnt/music_ssd/KKDJ/sorted/B/Boddhi Satva & James Germain/Boddhi Satva & James Germain An Nou Ale (Studio Bros Main Mix) - 8A - 125.mp3",
    "reason": "guardrail_violation",
    "details": ""
  },
  {
    "path": "/mnt/music_ssd/KKDJ/sorted/B/Boddhi Satva Kay Slice/Boddhi Satva Kay Slice - Out of This World (Main Mix) - 8A - 111.mp3",
    "reason": "guardrail_violation",
    "details": ""
  },
  {
    "path": "/mnt/music_ssd/KKDJ/sorted/B/Boddhi Satva Thandi Draai/Boddhi Satva Thandi Draai - Like Oooh (Main Mix) - 10A - 122.mp3",
    "reason": "guardrail_violation",
    "details": ""
  },
  {
    "path": "/mnt/music_ssd/KKDJ/sorted/B/Bongo Beats/Bongo Beats Ndive (feat. Bukeka) - 9B - 123.mp3",
    "reason": "guardrail_violation",
    "details": ""
  },
  {
    "path": "/mnt/music_ssd/KKDJ/sorted/B/Both 91/Second Choice - 12B - 124.mp3",
    "reason": "guardrail_violation",
    "details": ""
  },
  {
    "path": "/mnt/music_ssd/KKDJ/sorted/B/Brian Power, Rebecca Scales, N'dinga Gaba/Brian Power, Rebecca Scales, N'dinga Gaba So Long Gone (N'Dinga Gaba Afro Vocal Mix) - 7A - 125.mp3",
    "reason": "guardrail_violation",
    "details": ""
  },
  {
    "path": "/mnt/music_ssd/KKDJ/sorted/B/Bucie/Bucie Celi Ndoda (Point 5 Remix) - 2A - 124.mp3",
    "reason": "guardrail_violation",
    "details": ""
  },
  {
    "path": "/mnt/music_ssd/KKDJ/sorted/B/Bucie/Bucie Easy to Love (Zola EmoBoys Remix) - 1A - 122.mp3",
    "reason": "guardrail_violation",
    "details": ""
  },
  {
    "path": "/mnt/music_ssd/KKDJ/sorted/B/Bucie/Bucie Feat. Black Motion Rejoice - 9A - 125.mp3",
    "reason": "guardrail_violation",
    "details": ""
  },
  {
    "path": "/mnt/music_ssd/KKDJ/sorted/B/Bucie/Bucie Njabulo (feat. DJ Mshega) - 3A - 124.mp3",
    "reason": "guardrail_violation",
    "details": ""
  },
  {
    "path": "/mnt/music_ssd/KKDJ/sorted/B/Bucie/Bucie Shela (Original) - 3A - 125.mp3",
    "reason": "guardrail_violation",
    "details": ""
  },
  {
    "path": "/mnt/music_ssd/KKDJ/sorted/B/Bucie/Bucie ft. Heavy-K Easy To Love (Original) - 1A - 126.mp3",
    "reason": "guardrail_violation",
    "details": ""
  },
  {
    "path": "/mnt/music_ssd/KKDJ/sorted/B/Busi Mhlongo/Busi Mhlongo Webaba (Rocco Underground Mix) - 7A - 122.mp3",
    "reason": "guardrail_violation",
    "details": ""
  },
  {
    "path": "/mnt/music_ssd/KKDJ/sorted/B/Busiswa/Busiswa Feat. Oskido Ngoku (Uhuru Remake) - 1A - 125.mp3",
    "reason": "guardrail_violation",
    "details": ""
  },
  {
    "path": "/mnt/music_ssd/KKDJ/sorted/B/Busiswa/Busiswa ft. Oskido, Uhuru Lahla (Radio Edit) - 5A - 125.mp3",
    "reason": "guardrail_violation",
    "details": ""
  },
  {
    "path": "/mnt/music_ssd/KKDJ/sorted/B/The Blessed Madonna, Fred again/The Blessed Madonna, Fred again - Marea (we've lost dancing) (Original Mix) - 4A - 123.mp3",
    "reason": "guardrail_violation",
    "details": ""
  },
  {
    "path": "/mnt/music_ssd/KKDJ/sorted/C/Cafe 432/Pulling Up - 9A - 122.mp3",
    "reason": "guardrail_violation",
    "details": ""
  },
  {
    "path": "/mnt/music_ssd/KKDJ/sorted/C/Cafe De Anatolia, Alex Malagoli/Unadunda Feat Nicolas Tanda120 - 8A - 120.mp3",
    "reason": "guardrail_violation",
    "details": ""
  },
  {
    "path": "/mnt/music_ssd/KKDJ/sorted/C/Cafe De Anatolia, Pëtäk/Yemanjá120 - 10A - 120.mp3",
    "reason": "guardrail_violation",
    "details": ""
  },
  {
    "path": "/mnt/music_ssd/KKDJ/sorted/C/Caianda/Caianda No Telling - 2A - 123.mp3",
    "reason": "guardrail_violation",
    "details": ""
  },
  {
    "path": "/mnt/music_ssd/KKDJ/sorted/C/Caiiro/Caiiro Abiro (1) - 1A - 125.mp3",
    "reason": "guardrail_violation",
    "details": ""
  },
  {
    "path": "/mnt/music_ssd/KKDJ/sorted/C/Caiiro/Caiiro Abiro - 1A - 125.mp3",
    "reason": "guardrail_violation",
    "details": ""
  },
  {
    "path": "/mnt/music_ssd/KKDJ/sorted/C/Caiiro/Caiiro Abobaba - 8A - 123.mp3",
    "reason": "guardrail_violation",
    "details": ""
  },
  {
    "path": "/mnt/music_ssd/KKDJ/sorted/C/Caiiro/Caiiro Africa (1) - 8A - 126.mp3",
    "reason": "guardrail_violation",
    "details": ""
  },
  {
    "path": "/mnt/music_ssd/KKDJ/sorted/C/Caiiro/Caiiro Africa - 8A - 126.mp3",
    "reason": "guardrail_violation",
    "details": ""
  },
  {
    "path": "/mnt/music_ssd/KKDJ/sorted/C/Caiiro/Caiiro Agora - 1A - 120.mp3",
    "reason": "guardrail_violation",
    "details": ""
  },
  {
    "path": "/mnt/music_ssd/KKDJ/sorted/C/Caiiro/Caiiro Around Mars - 11A - 123.mp3",
    "reason": "guardrail_violation",
    "details": ""
  },
  {
    "path": "/mnt/music_ssd/KKDJ/sorted/C/Caiiro/Caiiro Bright Chamber - 5A - 122.mp3",
    "reason": "guardrail_violation",
    "details": ""
  },
  {
    "path": "/mnt/music_ssd/KKDJ/sorted/C/Caiiro/Caiiro D.I.M.P.H.O - 1A - 124.mp3",
    "reason": "guardrail_violation",
    "details": ""
  },
  {
    "path": "/mnt/music_ssd/KKDJ/sorted/C/Caiiro/Caiiro Drummotions (Original Mix) - 10A - 123.mp3",
    "reason": "guardrail_violation",
    "details": ""
  },
  {
    "path": "/mnt/music_ssd/KKDJ/sorted/C/Caiiro/Caiiro Drummotions - 10A - 123.mp3",
    "reason": "guardrail_violation",
    "details": ""
  },
  {
    "path": "/mnt/music_ssd/KKDJ/sorted/C/Caiiro/Caiiro Entabeni (feat. Pixie L) - 4A - 100.mp3",
    "reason": "guardrail_violation",
    "details": ""
  },
  {
    "path": "/mnt/music_ssd/KKDJ/sorted/C/Caiiro/Caiiro Feat. Dukanezwe Get Up - 7A - 123.mp3",
    "reason": "guardrail_violation",
    "details": ""
  },
  {
    "path": "/mnt/music_ssd/KKDJ/sorted/C/Caiiro/Caiiro Fela - 6A - 117.mp3",
    "reason": "guardrail_violation",
    "details": ""
  },
  {
    "path": "/mnt/music_ssd/KKDJ/sorted/C/Caiiro/Caiiro Herero - 6A - 123.mp3",
    "reason": "guardrail_violation",
    "details": ""
  },
  {
    "path": "/mnt/music_ssd/KKDJ/sorted/C/Caiiro/Caiiro Huhudi - 2A - 125.mp3",
    "reason": "guardrail_violation",
    "details": ""
  },
  {
    "path": "/mnt/music_ssd/KKDJ/sorted/C/Caiiro/Caiiro In Ibiza - 2A - 125.mp3",
    "reason": "guardrail_violation",
    "details": ""
  },
  {
    "path": "/mnt/music_ssd/KKDJ/sorted/C/Caiiro/Caiiro Kulum - 9A - 122.mp3",
    "reason": "guardrail_violation",
    "details": ""
  },
  {
    "path": "/mnt/music_ssd/KKDJ/sorted/C/Caiiro/Caiiro Kwipiri - 8A - 120.mp3",
    "reason": "guardrail_violation",
    "details": ""
  },
  {
    "path": "/mnt/music_ssd/KKDJ/sorted/C/Caiiro/Caiiro Moon Seeker - 12A - 126.mp3",
    "reason": "guardrail_violation",
    "details": ""
  },
  {
    "path": "/mnt/music_ssd/KKDJ/sorted/C/Caiiro/Caiiro Nakuru - 1A - 123.mp3",
    "reason": "guardrail_violation",
    "details": ""
  },
  {
    "path": "/mnt/music_ssd/KKDJ/sorted/C/Caiiro/Caiiro Namhlanj (feat. Kind) - 2A - 125.mp3",
    "reason": "guardrail_violation",
    "details": ""
  },
  {
    "path": "/mnt/music_ssd/KKDJ/sorted/C/Caiiro/Caiiro No Freedom - 6A - 123.mp3",
    "reason": "guardrail_violation",
    "details": ""
  },
  {
    "path": "/mnt/music_ssd/KKDJ/sorted/C/Caiiro/Caiiro Ntyilo Ntyilo (feat. Anda Cass) - 10A - 120.mp3",
    "reason": "guardrail_violation",
    "details": ""
  },
  {
    "path": "/mnt/music_ssd/KKDJ/sorted/C/Caiiro/Caiiro Thanda (feat. Pixie L) - 4A - 120.mp3",
    "reason": "guardrail_violation",
    "details": ""
  },
  {
    "path": "/mnt/music_ssd/KKDJ/sorted/C/Caiiro/Caiiro The Cure - 3A - 123.mp3",
    "reason": "guardrail_violation",
    "details": ""
  },
  {
    "path": "/mnt/music_ssd/KKDJ/sorted/C/Caiiro/Caiiro The Rise - 7A - 118.mp3",
    "reason": "guardrail_violation",
    "details": ""
  },
  {
    "path": "/mnt/music_ssd/KKDJ/sorted/C/Caiiro/Caiiro The Violin (Afro House Remix) - 4A - 124.mp3",
    "reason": "guardrail_violation",
    "details": ""
  },
  {
    "path": "/mnt/music_ssd/KKDJ/sorted/C/Caiiro/Caiiro Vuselela (feat. Mpumi) - 5A - 122.mp3",
    "reason": "guardrail_violation",
    "details": ""
  },
  {
    "path": "/mnt/music_ssd/KKDJ/sorted/C/Caiiro/Caiiro Yawela - 5A - 120.mp3",
    "reason": "guardrail_violation",
    "details": ""
  },
  {
    "path": "/mnt/music_ssd/KKDJ/sorted/C/Caiiro/Caiiro Yi Drada (1) - 11A - 125.mp3",
    "reason": "guardrail_violation",
    "details": ""
  },
  {
    "path": "/mnt/music_ssd/KKDJ/sorted/C/Caiiro/Caiiro Yi Drada - 11A - 125.mp3",
    "reason": "guardrail_violation",
    "details": ""
  },
  {
    "path": "/mnt/music_ssd/KKDJ/sorted/C/Candy Man/Candy Man Raw - 5A - 125.mp3",
    "reason": "guardrail_violation",
    "details": ""
  },
  {
    "path": "/mnt/music_ssd/KKDJ/sorted/C/Candy Man/Candy Man Technokrat - 4A - 123.mp3",
    "reason": "guardrail_violation",
    "details": ""
  },
  {
    "path": "/mnt/music_ssd/KKDJ/sorted/C/Candyman, Rabs Vhafuwi/Candyman, Rabs Vhafuwi Limpopo Ruler (1) - 5A - 125.mp3",
    "reason": "guardrail_violation",
    "details": ""
  },
  {
    "path": "/mnt/music_ssd/KKDJ/sorted/C/Candyman, Rabs Vhafuwi/Candyman, Rabs Vhafuwi Limpopo Ruler - 5A - 125.mp3",
    "reason": "guardrail_violation",
    "details": ""
  },
  {
    "path": "/mnt/music_ssd/KKDJ/sorted/C/Cassius/Cassius 1999 - 8A - 127.mp3",
    "reason": "guardrail_violation",
    "details": ""
  },
  {
    "path": "/mnt/music_ssd/KKDJ/sorted/C/Catzico, Lizwi/Catzico, Lizwi Wezinsizwa (Kususa, Soulholic & 7Options Remix) - 10A - 124.mp3",
    "reason": "guardrail_violation",
    "details": ""
  },
  {
    "path": "/mnt/music_ssd/KKDJ/sorted/C/Cee ElAssaad/Cee ElAssaad, Jackie Queens All On You (HyperSOUL-X HT Remix) - 5A - 123.mp3",
    "reason": "guardrail_violation",
    "details": ""
  },
  {
    "path": "/mnt/music_ssd/KKDJ/sorted/C/Ch!njong X Ch!njong/Ch!njong X Ch!njong Tribalismo - 2A - 122.mp3",
    "reason": "guardrail_violation",
    "details": ""
  },
  {
    "path": "/mnt/music_ssd/KKDJ/sorted/C/Charles Webster/Giving Love - 7A - 124.mp3",
    "reason": "guardrail_violation",
    "details": ""
  },
  {
    "path": "/mnt/music_ssd/KKDJ/sorted/C/Chase & Status feat. Plan B/End Credits - 12A - 87.mp3",
    "reason": "guardrail_violation",
    "details": ""
  },
  {
    "path": "/mnt/music_ssd/KKDJ/sorted/C/Chiwasa/Chiwasa Moyo - 8A - 126.mp3",
    "reason": "guardrail_violation",
    "details": ""
  },
  {
    "path": "/mnt/music_ssd/KKDJ/sorted/C/Chomee/Chomee Hamba Uyolala (Part 2) [feat. Professor & Trademark] - 11A - 125.mp3",
    "reason": "guardrail_violation",
    "details": ""
  },
  {
    "path": "/mnt/music_ssd/KKDJ/sorted/C/Chomee X Professor/Chomee X Professor Amaplan - 9A - 125.mp3",
    "reason": "guardrail_violation",
    "details": ""
  },
  {
    "path": "/mnt/music_ssd/KKDJ/sorted/C/Chrisoul Inactive, Lungi Mandebele, Trinity/Chrisoul Inactive, Lungi Mandebele, Trinity Isizwe (Afro Mix) - 2A - 123.mp3",
    "reason": "guardrail_violation",
    "details": ""
  },
  {
    "path": "/mnt/music_ssd/KKDJ/sorted/C/Christos Fourkis/Christos Fourkis Djembe Fever (Original Mix) - 5A - 122.mp3",
    "reason": "guardrail_violation",
    "details": ""
  },
  {
    "path": "/mnt/music_ssd/KKDJ/sorted/C/Christos Fourkis/Christos Fourkis Djembe Fever - 5A - 122.mp3",
    "reason": "guardrail_violation",
    "details": ""
  },
  {
    "path": "/mnt/music_ssd/KKDJ/sorted/C/Christos Fourkis/Christos Fourkis Doumasi (1) - 5A - 123.mp3",
    "reason": "guardrail_violation",
    "details": ""
  },
  {
    "path": "/mnt/music_ssd/KKDJ/sorted/C/Christos Fourkis/Christos Fourkis Doumasi - 5A - 123.mp3",
    "reason": "guardrail_violation",
    "details": ""
  },
  {
    "path": "/mnt/music_ssd/KKDJ/sorted/C/Christos Fourkis/Christos Fourkis Summer Love feat. Joahn Dashi (Stones & Bones Remix) (1) - 8A - 122.mp3",
    "reason": "guardrail_violation",
    "details": ""
  },
  {
    "path": "/mnt/music_ssd/KKDJ/sorted/C/Chynaman Kususa Argento Dust Azola/Chynaman Kususa Argento Dust Azola - Just Love (Edit) - 11A - 123.mp3",
    "reason": "guardrail_violation",
    "details": ""
  },
  {
    "path": "/mnt/music_ssd/KKDJ/sorted/C/Citizen Deep & Mash.O Feat. Tsoseletso/Citizen Deep & Mash.O Feat. Tsoseletso Falling - 6A - 123.mp3",
    "reason": "guardrail_violation",
    "details": ""
  },
  {
    "path": "/mnt/music_ssd/KKDJ/sorted/C/Claudio Ricci, Megablast/Claudio Ricci, Megablast Amour (Brigado Crew African Remix) - 7A - 123.mp3",
    "reason": "guardrail_violation",
    "details": ""
  },
  {
    "path": "/mnt/music_ssd/KKDJ/sorted/C/Copyright Featuring Andre Espeut/Lifted - 5A - 125.mp3",
    "reason": "guardrail_violation",
    "details": ""
  },
  {
    "path": "/mnt/music_ssd/KKDJ/sorted/C/Cristian Vinci/Cristian Vinci Nairobi (1) - 6A - 123.mp3",
    "reason": "guardrail_violation",
    "details": ""
  },
  {
    "path": "/mnt/music_ssd/KKDJ/sorted/C/Cristian Vinci/Cristian Vinci Nairobi - 6A - 123.mp3",
    "reason": "guardrail_violation",
    "details": ""
  },
  {
    "path": "/mnt/music_ssd/KKDJ/sorted/C/Cuebur/Cuebur Tamba (Feat. DJ Maphorisa & Sha Sha) (1) - 2A - 122.mp3",
    "reason": "guardrail_violation",
    "details": ""
  },
  {
    "path": "/mnt/music_ssd/KKDJ/sorted/C/Cuebur/Cuebur Tamba (Feat. DJ Maphorisa & Sha Sha) - 2A - 122.mp3",
    "reason": "guardrail_violation",
    "details": ""
  },
  {
    "path": "/mnt/music_ssd/KKDJ/sorted/C/Culoe De Song/Culoe De Song - Hold Strong (Album Version) - 8A - 124.mp3",
    "reason": "guardrail_violation",
    "details": ""
  },
  {
    "path": "/mnt/music_ssd/KKDJ/sorted/C/Culoe De Song/Culoe De Song - The One (Album Version) - 10A - 124.mp3",
    "reason": "guardrail_violation",
    "details": ""
  },
  {
    "path": "/mnt/music_ssd/KKDJ/sorted/C/Culoe De Song/Culoe De Song - Yini Ngawe (Album Version) - 7A - 124.mp3",
    "reason": "guardrail_violation",
    "details": ""
  },
  {
    "path": "/mnt/music_ssd/KKDJ/sorted/C/Culoe De Song/Culoe De Song Ambush - 11A - 125.mp3",
    "reason": "guardrail_violation",
    "details": ""
  },
  {
    "path": "/mnt/music_ssd/KKDJ/sorted/C/Culoe De Song/Culoe De Song Gyser - 6A - 125.mp3",
    "reason": "guardrail_violation",
    "details": ""
  },
  {
    "path": "/mnt/music_ssd/KKDJ/sorted/C/Culoe De Song/Culoe De Song Woman Woman - 7A - 124.mp3",
    "reason": "guardrail_violation",
    "details": ""
  },
  {
    "path": "/mnt/music_ssd/KKDJ/sorted/C/Culoe De Song/Culoe De Song Y.O.U.D - 6A - 125.mp3",
    "reason": "guardrail_violation",
    "details": ""
  },
  {
    "path": "/mnt/music_ssd/KKDJ/sorted/C/Culoe De Song/Culoe De Song ft. Thandiswa Mazwai Nguwe Lo (Original) - 10A - 124.mp3",
    "reason": "guardrail_violation",
    "details": ""
  },
  {
    "path": "/mnt/music_ssd/KKDJ/sorted/C/Culoe De Song/Culoe de Song Webaba - 8A - 122.mp3",
    "reason": "guardrail_violation",
    "details": ""
  },
  {
    "path": "/mnt/music_ssd/KKDJ/sorted/D/D Banj/D Banj Oliver Twist (Triger Sixkay Remix) - 1A - 125.mp3",
    "reason": "guardrail_violation",
    "details": ""
  },
  {
    "path": "/mnt/music_ssd/KKDJ/sorted/D/D-zaya Feat. Shisaboy/D-zaya Feat. Shisaboy BBM Dance(AirDrumz Original - 7A - 125.mp3",
    "reason": "guardrail_violation",
    "details": ""
  },
  {
    "path": "/mnt/music_ssd/KKDJ/sorted/D/D.General, Mahume, Those Boys, Mr. Lee, Thandi Draai, DeependSoul/D.General, Mahume, Those Boys, Mr. Lee, Thandi Draai, DeependSoul Misconception - 1A - 122.mp3",
    "reason": "low_confidence",
    "details": ""
  },
  {
    "path": "/mnt/music_ssd/KKDJ/sorted/D/DASCO/DASCO African Power - 4A - 124.mp3",
    "reason": "guardrail_violation",
    "details": ""
  },
  {
    "path": "/mnt/music_ssd/KKDJ/sorted/D/DJ Angelo/DJ Angelo Carnaval Dream - 8A - 122.mp3",
    "reason": "guardrail_violation",
    "details": ""
  },
  {
    "path": "/mnt/music_ssd/KKDJ/sorted/D/DJ Angelo/DJ Angelo Sira Kuruni (feat. Farafi) - 11A - 122.mp3",
    "reason": "guardrail_violation",
    "details": ""
  }
]
